web/dispatch/resource/__init__.py
web/dispatch/resource/dispatch.py
web/dispatch/resource/exc.py
web/dispatch/resource/helper.py
web/dispatch/resource/release.py
web/dispatch/resource/__pycache__/__init__.cpython-37.opt-1.pyc
web/dispatch/resource/__pycache__/dispatch.cpython-37.opt-1.pyc
web/dispatch/resource/__pycache__/exc.cpython-37.opt-1.pyc
web/dispatch/resource/__pycache__/helper.cpython-37.opt-1.pyc
web/dispatch/resource/__pycache__/release.cpython-37.opt-1.pyc
web.dispatch.resource-3.0.0.dist-info/LICENSE.txt
web.dispatch.resource-3.0.0.dist-info/METADATA
web.dispatch.resource-3.0.0.dist-info/WHEEL
web.dispatch.resource-3.0.0.dist-info/entry_points.txt
web.dispatch.resource-3.0.0.dist-info/top_level.txt
web.dispatch.resource-3.0.0.dist-info/RECORD
