Metadata-Version: 2.1
Name: web.dispatch.resource
Version: 3.0.0
Summary: Resource dispatch; a method to resolve a request to an endopint using the WSGI HTTP_METHOD and attribute access.
Home-page: https://github.com/marrow/web.dispatch.resource
Author: Alice Bevan-McGregor
Author-email: alice@gothcandy.com
License: MIT
Download-URL: https://github.com/marrow/web.dispatch.resource/releases
Project-URL: Repository, https://github.com/marrow/web.dispatch.resource/
Project-URL: Documentation, https://github.com/marrow/web.dispatch.resource/#readme
Project-URL: Issue Tracker, https://github.com/marrow/web.dispatch.resource/issues
Project-URL: Funding, https://www.patreon.com/GothAlice
Keywords: marrow,dispatch,web.dispatch,resource dispatch,endpoint discovery,WebCore,REST
Platform: UNKNOWN
Classifier: Development Status :: 5 - Production/Stable
Classifier: Environment :: Console
Classifier: Environment :: Web Environment
Classifier: Intended Audience :: Developers
Classifier: License :: OSI Approved :: MIT License
Classifier: Operating System :: OS Independent
Classifier: Programming Language :: Python
Classifier: Programming Language :: Python :: 3
Classifier: Programming Language :: Python :: 3.6
Classifier: Programming Language :: Python :: 3.7
Classifier: Programming Language :: Python :: 3.8
Classifier: Programming Language :: Python :: Implementation :: CPython
Classifier: Programming Language :: Python :: Implementation :: PyPy
Classifier: Topic :: Software Development :: Libraries :: Python Modules
Requires-Dist: web.dispatch (~=3.0.1)
Provides-Extra: development
Requires-Dist: pytest ; extra == 'development'
Requires-Dist: pytest-cov ; extra == 'development'
Requires-Dist: pytest-flakes ; extra == 'development'
Requires-Dist: pytest-catchlog ; extra == 'development'
Requires-Dist: WebOb ; extra == 'development'
Requires-Dist: pre-commit ; extra == 'development'
